hhfactor/__init__.py
hhfactor/basicdataupdate.py
hhfactor/calcucore.py
hhfactor/factor.py
hhfactor/algor/__init__.py
hhfactor/algor/datetreatment.py
hhfactor/algor/factoralgo.py
hhfactor/algor/factortreatment.py
hhfactor/analyze/__init__.py
hhfactor/analyze/analysis.py
hhfactor/data/tradedate.json
hhfactor-1.7.dist-info/METADATA
hhfactor-1.7.dist-info/WHEEL
hhfactor-1.7.dist-info/top_level.txt
hhfactor-1.7.dist-info/RECORD
