Metadata-Version: 2.2
Name: hhfactor
Version: 1.7
Summary: factor
Home-page: https://your.project.url
Author: hh
Author-email: hehuang0717@outlook.com
Classifier: Programming Language :: Python :: 3
Classifier: License :: OSI Approved :: MIT License
Classifier: Operating System :: OS Independent
Requires-Python: >=3.12
Requires-Dist: h5py
Requires-Dist: tables
Dynamic: author
Dynamic: author-email
Dynamic: classifier
Dynamic: description
Dynamic: description-content-type
Dynamic: home-page
Dynamic: requires-dist
Dynamic: requires-python
Dynamic: summary
